README.md
setup.cfg
setup.py
flask_stateless_auth/__init__.py
flask_stateless_auth.egg-info/PKG-INFO
flask_stateless_auth.egg-info/SOURCES.txt
flask_stateless_auth.egg-info/dependency_links.txt
flask_stateless_auth.egg-info/requires.txt
flask_stateless_auth.egg-info/top_level.txt
tests/__init__.py
tests/app_example.py
tests/test_app.py