Metadata-Version: 2.1
Name: flask-stateless-auth
Version: 0.0.17
Summary: Flask stateless authentication with secrets
Home-page: https://github.com/omarryhan/flask-stateless-auth
Author: Omar Ryhan
Author-email: omarryhan@gmail.com
License: MIT
Platform: UNKNOWN
Classifier: Programming Language :: Python :: 3
Classifier: License :: OSI Approved :: MIT License
Classifier: Operating System :: OS Independent
